{
    "data": [
        {
            "topic": "invite",
            "groupName": "onlineInviteApply",
            "backupTime": "19:59:17",
            "message": "{\"applyId\":\"0\",\"applyTime\":\"2016-11-04 19:59:14\",\"inviteId\":\"0\",\"userId\":\"680212469\",\"inviteTime\":\"2016-11-04 19:59:14\",\"rootCompanyId\":\"34834458\",\"companyId\":\"34834458\",\"isFeedback\":\"false\",\"resumeSource\":\"5\",\"isFilter\":\"false\",\"isRepeat\":\"false\",\"resume\":{\"number\":\"JM802124697R90250000000\",\"id\":\"250915157\",\"version\":\"1\"},\"job\":{\"id\":\"31244046954\",\"number\":\"CC348344587J90250044000\",\"editId\":\"202195584\",\"cityId\":\"731\",\"version\":\"1\"},\"inviteStatus\":\"0\"}"
        },
         {
            "topic": "invite",
            "groupName": "onlineInviteApply",
            "backupTime": "19:59:17",
            "message": "{\"applyId\":\"0\",\"applyTime\":\"2016-11-04 19:59:14\",\"inviteId\":\"0\",\"userId\":\"680212469\",\"inviteTime\":\"2016-11-04 19:59:14\",\"rootCompanyId\":\"34834458\",\"companyId\":\"34834458\",\"isFeedback\":\"false\",\"resumeSource\":\"5\",\"isFilter\":\"false\",\"isRepeat\":\"false\",\"resume\":{\"number\":\"JM802124697R90250000000\",\"id\":\"250915157\",\"version\":\"1\"},\"job\":{\"id\":\"31244046954\",\"number\":\"CC348344587J90250044000\",\"editId\":\"202195584\",\"cityId\":\"731\",\"version\":\"1\"},\"inviteStatus\":\"0\"}"
        },
         {
            "topic": "invite",
            "groupName": "onlineInviteApply",
            "backupTime": "19:59:17",
            "message": "{\"applyId\":\"0\",\"applyTime\":\"2016-11-04 19:59:14\",\"inviteId\":\"0\",\"userId\":\"680212469\",\"inviteTime\":\"2016-11-04 19:59:14\",\"rootCompanyId\":\"34834458\",\"companyId\":\"34834458\",\"isFeedback\":\"false\",\"resumeSource\":\"5\",\"isFilter\":\"false\",\"isRepeat\":\"false\",\"resume\":{\"number\":\"JM802124697R90250000000\",\"id\":\"250915157\",\"version\":\"1\"},\"job\":{\"id\":\"31244046954\",\"number\":\"CC348344587J90250044000\",\"editId\":\"202195584\",\"cityId\":\"731\",\"version\":\"1\"},\"inviteStatus\":\"0\"}"
        },
         {
            "topic": "invite",
            "groupName": "onlineInviteApply",
            "backupTime": "19:59:17",
            "message": "{\"applyId\":\"0\",\"applyTime\":\"2016-11-04 19:59:14\",\"inviteId\":\"0\",\"userId\":\"680212469\",\"inviteTime\":\"2016-11-04 19:59:14\",\"rootCompanyId\":\"34834458\",\"companyId\":\"34834458\",\"isFeedback\":\"false\",\"resumeSource\":\"5\",\"isFilter\":\"false\",\"isRepeat\":\"false\",\"resume\":{\"number\":\"JM802124697R90250000000\",\"id\":\"250915157\",\"version\":\"1\"},\"job\":{\"id\":\"31244046954\",\"number\":\"CC348344587J90250044000\",\"editId\":\"202195584\",\"cityId\":\"731\",\"version\":\"1\"},\"inviteStatus\":\"0\"}"
        },
         {
            "topic": "invite",
            "groupName": "onlineInviteApply",
            "backupTime": "19:59:17",
            "message": "{\"applyId\":\"0\",\"applyTime\":\"2016-11-04 19:59:14\",\"inviteId\":\"0\",\"userId\":\"680212469\",\"inviteTime\":\"2016-11-04 19:59:14\",\"rootCompanyId\":\"34834458\",\"companyId\":\"34834458\",\"isFeedback\":\"false\",\"resumeSource\":\"5\",\"isFilter\":\"false\",\"isRepeat\":\"false\",\"resume\":{\"number\":\"JM802124697R90250000000\",\"id\":\"250915157\",\"version\":\"1\"},\"job\":{\"id\":\"31244046954\",\"number\":\"CC348344587J90250044000\",\"editId\":\"202195584\",\"cityId\":\"731\",\"version\":\"1\"},\"inviteStatus\":\"0\"}"
        },
         {
            "topic": "invite",
            "groupName": "onlineInviteApply",
            "backupTime": "19:59:17",
            "message": "{\"applyId\":\"0\",\"applyTime\":\"2016-11-04 19:59:14\",\"inviteId\":\"0\",\"userId\":\"680212469\",\"inviteTime\":\"2016-11-04 19:59:14\",\"rootCompanyId\":\"34834458\",\"companyId\":\"34834458\",\"isFeedback\":\"false\",\"resumeSource\":\"5\",\"isFilter\":\"false\",\"isRepeat\":\"false\",\"resume\":{\"number\":\"JM802124697R90250000000\",\"id\":\"250915157\",\"version\":\"1\"},\"job\":{\"id\":\"31244046954\",\"number\":\"CC348344587J90250044000\",\"editId\":\"202195584\",\"cityId\":\"731\",\"version\":\"1\"},\"inviteStatus\":\"0\"}"
        },
         {
            "topic": "invite",
            "groupName": "onlineInviteApply",
            "backupTime": "19:59:17",
            "message": "{\"applyId\":\"0\",\"applyTime\":\"2016-11-04 19:59:14\",\"inviteId\":\"0\",\"userId\":\"680212469\",\"inviteTime\":\"2016-11-04 19:59:14\",\"rootCompanyId\":\"34834458\",\"companyId\":\"34834458\",\"isFeedback\":\"false\",\"resumeSource\":\"5\",\"isFilter\":\"false\",\"isRepeat\":\"false\",\"resume\":{\"number\":\"JM802124697R90250000000\",\"id\":\"250915157\",\"version\":\"1\"},\"job\":{\"id\":\"31244046954\",\"number\":\"CC348344587J90250044000\",\"editId\":\"202195584\",\"cityId\":\"731\",\"version\":\"1\"},\"inviteStatus\":\"0\"}"
        },
         {
            "topic": "invite",
            "groupName": "onlineInviteApply",
            "backupTime": "19:59:17",
            "message": "{\"applyId\":\"0\",\"applyTime\":\"2016-11-04 19:59:14\",\"inviteId\":\"0\",\"userId\":\"680212469\",\"inviteTime\":\"2016-11-04 19:59:14\",\"rootCompanyId\":\"34834458\",\"companyId\":\"34834458\",\"isFeedback\":\"false\",\"resumeSource\":\"5\",\"isFilter\":\"false\",\"isRepeat\":\"false\",\"resume\":{\"number\":\"JM802124697R90250000000\",\"id\":\"250915157\",\"version\":\"1\"},\"job\":{\"id\":\"31244046954\",\"number\":\"CC348344587J90250044000\",\"editId\":\"202195584\",\"cityId\":\"731\",\"version\":\"1\"},\"inviteStatus\":\"0\"}"
        },
         {
            "topic": "invite",
            "groupName": "onlineInviteApply",
            "backupTime": "19:59:17",
            "message": "{\"applyId\":\"0\",\"applyTime\":\"2016-11-04 19:59:14\",\"inviteId\":\"0\",\"userId\":\"680212469\",\"inviteTime\":\"2016-11-04 19:59:14\",\"rootCompanyId\":\"34834458\",\"companyId\":\"34834458\",\"isFeedback\":\"false\",\"resumeSource\":\"5\",\"isFilter\":\"false\",\"isRepeat\":\"false\",\"resume\":{\"number\":\"JM802124697R90250000000\",\"id\":\"250915157\",\"version\":\"1\"},\"job\":{\"id\":\"31244046954\",\"number\":\"CC348344587J90250044000\",\"editId\":\"202195584\",\"cityId\":\"731\",\"version\":\"1\"},\"inviteStatus\":\"0\"}"
        },
         {
            "topic": "invite",
            "groupName": "onlineInviteApply",
            "backupTime": "19:59:17",
            "message": "{\"applyId\":\"0\",\"applyTime\":\"2016-11-04 19:59:14\",\"inviteId\":\"0\",\"userId\":\"680212469\",\"inviteTime\":\"2016-11-04 19:59:14\",\"rootCompanyId\":\"34834458\",\"companyId\":\"34834458\",\"isFeedback\":\"false\",\"resumeSource\":\"5\",\"isFilter\":\"false\",\"isRepeat\":\"false\",\"resume\":{\"number\":\"JM802124697R90250000000\",\"id\":\"250915157\",\"version\":\"1\"},\"job\":{\"id\":\"31244046954\",\"number\":\"CC348344587J90250044000\",\"editId\":\"202195584\",\"cityId\":\"731\",\"version\":\"1\"},\"inviteStatus\":\"0\"}"
        },
         {
            "topic": "invite",
            "groupName": "onlineInviteApply",
            "backupTime": "19:59:17",
            "message": "{\"applyId\":\"0\",\"applyTime\":\"2016-11-04 19:59:14\",\"inviteId\":\"0\",\"userId\":\"680212469\",\"inviteTime\":\"2016-11-04 19:59:14\",\"rootCompanyId\":\"34834458\",\"companyId\":\"34834458\",\"isFeedback\":\"false\",\"resumeSource\":\"5\",\"isFilter\":\"false\",\"isRepeat\":\"false\",\"resume\":{\"number\":\"JM802124697R90250000000\",\"id\":\"250915157\",\"version\":\"1\"},\"job\":{\"id\":\"31244046954\",\"number\":\"CC348344587J90250044000\",\"editId\":\"202195584\",\"cityId\":\"731\",\"version\":\"1\"},\"inviteStatus\":\"0\"}"
        },
         {
            "topic": "invite",
            "groupName": "onlineInviteApply",
            "backupTime": "19:59:17",
            "message": "{\"applyId\":\"0\",\"applyTime\":\"2016-11-04 19:59:14\",\"inviteId\":\"0\",\"userId\":\"680212469\",\"inviteTime\":\"2016-11-04 19:59:14\",\"rootCompanyId\":\"34834458\",\"companyId\":\"34834458\",\"isFeedback\":\"false\",\"resumeSource\":\"5\",\"isFilter\":\"false\",\"isRepeat\":\"false\",\"resume\":{\"number\":\"JM802124697R90250000000\",\"id\":\"250915157\",\"version\":\"1\"},\"job\":{\"id\":\"31244046954\",\"number\":\"CC348344587J90250044000\",\"editId\":\"202195584\",\"cityId\":\"731\",\"version\":\"1\"},\"inviteStatus\":\"0\"}"
        },
         {
            "topic": "invite",
            "groupName": "onlineInviteApply",
            "backupTime": "19:59:17",
            "message": "{\"applyId\":\"0\",\"applyTime\":\"2016-11-04 19:59:14\",\"inviteId\":\"0\",\"userId\":\"680212469\",\"inviteTime\":\"2016-11-04 19:59:14\",\"rootCompanyId\":\"34834458\",\"companyId\":\"34834458\",\"isFeedback\":\"false\",\"resumeSource\":\"5\",\"isFilter\":\"false\",\"isRepeat\":\"false\",\"resume\":{\"number\":\"JM802124697R90250000000\",\"id\":\"250915157\",\"version\":\"1\"},\"job\":{\"id\":\"31244046954\",\"number\":\"CC348344587J90250044000\",\"editId\":\"202195584\",\"cityId\":\"731\",\"version\":\"1\"},\"inviteStatus\":\"0\"}"
        },
         {
            "topic": "invite",
            "groupName": "onlineInviteApply",
            "backupTime": "19:59:17",
            "message": "{\"applyId\":\"0\",\"applyTime\":\"2016-11-04 19:59:14\",\"inviteId\":\"0\",\"userId\":\"680212469\",\"inviteTime\":\"2016-11-04 19:59:14\",\"rootCompanyId\":\"34834458\",\"companyId\":\"34834458\",\"isFeedback\":\"false\",\"resumeSource\":\"5\",\"isFilter\":\"false\",\"isRepeat\":\"false\",\"resume\":{\"number\":\"JM802124697R90250000000\",\"id\":\"250915157\",\"version\":\"1\"},\"job\":{\"id\":\"31244046954\",\"number\":\"CC348344587J90250044000\",\"editId\":\"202195584\",\"cityId\":\"731\",\"version\":\"1\"},\"inviteStatus\":\"0\"}"
        },
         {
            "topic": "invite",
            "groupName": "onlineInviteApply",
            "backupTime": "19:59:17",
            "message": "{\"applyId\":\"0\",\"applyTime\":\"2016-11-04 19:59:14\",\"inviteId\":\"0\",\"userId\":\"680212469\",\"inviteTime\":\"2016-11-04 19:59:14\",\"rootCompanyId\":\"34834458\",\"companyId\":\"34834458\",\"isFeedback\":\"false\",\"resumeSource\":\"5\",\"isFilter\":\"false\",\"isRepeat\":\"false\",\"resume\":{\"number\":\"JM802124697R90250000000\",\"id\":\"250915157\",\"version\":\"1\"},\"job\":{\"id\":\"31244046954\",\"number\":\"CC348344587J90250044000\",\"editId\":\"202195584\",\"cityId\":\"731\",\"version\":\"1\"},\"inviteStatus\":\"0\"}"
        }
    ],
    "numFound": 15
}